ruptured/__init__.py
ruptured/example.py
ruptured-0.1.0.dist-info/LICENSE
ruptured-0.1.0.dist-info/METADATA
ruptured-0.1.0.dist-info/WHEEL
ruptured-0.1.0.dist-info/top_level.txt
ruptured-0.1.0.dist-info/RECORD
