Metadata-Version: 2.1
Name: ruptured
Version: 0.1.0
Summary: A game-creating module that focuses on ui
Author-email: Bruce Li <isanoob1897@outlook.com>
Project-URL: Homepage, https://github.com/Bruceli-iscool/Ruptured
Project-URL: Issues, https://github.com/Bruceli-iscool/Ruptured/issues
Classifier: Programming Language :: Python :: 3
Classifier: License :: OSI Approved :: MIT License
Classifier: Operating System :: OS Independent
Requires-Python: >=3.8
License-File: LICENSE
